COPYING.txt
MANIFEST.in
README.txt
mylit.py
setup.py
mylit.egg-info/PKG-INFO
mylit.egg-info/SOURCES.txt
mylit.egg-info/dependency_links.txt
mylit.egg-info/top_level.txt