Metadata-Version: 1.0
Name: mylit
Version: 0.1.2
Summary: Literate programming for Python
Home-page: http://packages.python.org/mylit
Author: Stephan Wenger
Author-email: wenger@cg.cs.tu-bs.de
License: MIT
Download-URL: http://pypi.python.org/pypi/mylit
Keywords: literate programming
Platform: UNKNOWN
Classifier: Programming Language :: Python
Classifier: Programming Language :: Python :: 2
Classifier: License :: OSI Approved :: MIT License
Classifier: Operating System :: OS Independent
Classifier: Development Status :: 4 - Beta
Classifier: Environment :: Other Environment
Classifier: Intended Audience :: Developers
Classifier: Topic :: Documentation
Classifier: Topic :: Software Development :: Documentation
Classifier: Topic :: Software Development :: Libraries :: Python Modules
Classifier: Topic :: Text Processing :: Filters
Classifier: Topic :: Text Processing :: Markup :: HTML
